google_form_api/__init__.py
google_form_api/main.py
google_form_api-0.1.0.dist-info/METADATA
google_form_api-0.1.0.dist-info/WHEEL
google_form_api-0.1.0.dist-info/RECORD
